MANIFEST.in
setup.py
src/ua2/__init__.py
src/ua2.ajax.egg-info/PKG-INFO
src/ua2.ajax.egg-info/SOURCES.txt
src/ua2.ajax.egg-info/dependency_links.txt
src/ua2.ajax.egg-info/eager_resources.txt
src/ua2.ajax.egg-info/namespace_packages.txt
src/ua2.ajax.egg-info/not-zip-safe
src/ua2.ajax.egg-info/top_level.txt
src/ua2/ajax/__init__.py
src/ua2/ajax/accept_ajax.py
src/ua2/ajax/static/js/ua2ajax.js