Metadata-Version: 1.0
Name: ua2.ajax
Version: 0.1.3
Summary: Django Ajax wrapper
Home-page: https://bitbucket.org/ua2web/ua2.ajax
Author: Vic
Author-email: vic@ua2crm.com
License: BSD License
Platform: UNKNOWN
